django_hstore_widget/__init__.py
django_hstore_widget/apps.py
django_hstore_widget/checks.py
django_hstore_widget/forms.py
django_hstore_widget/widgets.py
django_hstore_widget/migrations/0001_initial.py
django_hstore_widget/migrations/__init__.py
django_hstore_widget/static/admin/js/django_hstore_widget/django-hstore-widget.js
django_hstore_widget/static/admin/js/django_hstore_widget/image-icon.js
django_hstore_widget/static/admin/js/django_hstore_widget/index.js
django_hstore_widget/static/admin/js/django_hstore_widget/p-DEkVJ2lr.js
django_hstore_widget/templates/django_hstore_widget.html
django_hstore_widget-0.0.24.dist-info/METADATA
django_hstore_widget-0.0.24.dist-info/WHEEL
django_hstore_widget-0.0.24.dist-info/licenses/LICENSE
django_hstore_widget-0.0.24.dist-info/RECORD
