Metadata-Version: 2.4
Name: django-hstore-widget
Version: 0.0.24
Summary: Human friendly HStoreWidget. Continual of django-admin-hstore-widget.
Project-URL: Homepage, https://github.com/baseplate-admin/django-hstore-widget
Project-URL: Repository, https://github.com/baseplate-admin/django-hstore-widget
Project-URL: Bug Tracker, https://github.com/baseplate-admin/django-hstore-widget/issues
Author-email: baseplate-admin <61817579+baseplate-admin@users.noreply.github.com>, Alexandre Dufour <adufour@poka.io>
Maintainer-email: baseplate-admin <61817579+baseplate-admin@users.noreply.github.com>
License: MIT
License-File: LICENSE
Classifier: Development Status :: 5 - Production/Stable
Classifier: Framework :: Django
Classifier: Framework :: Django :: 2.2
Classifier: Framework :: Django :: 3.1
Classifier: Framework :: Django :: 3.2
Classifier: Framework :: Django :: 4.1
Classifier: Framework :: Django :: 4.2
Classifier: Framework :: Django :: 5.0
Classifier: Framework :: Django :: 5.1
Classifier: Framework :: Django :: 5.2
Classifier: Intended Audience :: Developers
Classifier: License :: OSI Approved :: MIT License
Classifier: Operating System :: OS Independent
Classifier: Programming Language :: Python
Classifier: Programming Language :: Python :: 3
Classifier: Programming Language :: Python :: 3.10
Classifier: Programming Language :: Python :: 3.11
Classifier: Programming Language :: Python :: 3.12
Classifier: Programming Language :: Python :: 3.13
Classifier: Programming Language :: Python :: 3.14
Classifier: Programming Language :: Python :: Implementation :: CPython
Classifier: Programming Language :: Python :: Implementation :: PyPy
Classifier: Topic :: Software Development :: Libraries :: Python Modules
Requires-Python: >=3.10
Requires-Dist: django
